django_deep_link/__init__.py
django_deep_link/admin.py
django_deep_link/apps.py
django_deep_link/dtos.py
django_deep_link/mixins.py
django_deep_link/models.py
django_deep_link/settings.py
django_deep_link/urls.py
django_deep_link/views.py
django_deep_link/helpers/__init__.py
django_deep_link/helpers/ip.py
django_deep_link/helpers/ua.py
django_deep_link/helpers/url.py
django_deep_link/helpers/tests/__init__.py
django_deep_link/helpers/tests/test_ip.py
django_deep_link/helpers/tests/test_ua.py
django_deep_link/migrations/0001_initial.py
django_deep_link/migrations/0002_alter_visit_ip_address_alter_visit_ip_data_and_more.py
django_deep_link/migrations/0003_alter_visit_ip_address_alter_visit_ip_data_and_more.py
django_deep_link/migrations/__init__.py
django_deep_link/templates/django_deep_link/app.html
django_deep_link/templates/django_deep_link/base.html
django_deep_link-0.3.1.dist-info/AUTHORS.md
django_deep_link-0.3.1.dist-info/LICENSE
django_deep_link-0.3.1.dist-info/METADATA
django_deep_link-0.3.1.dist-info/WHEEL
django_deep_link-0.3.1.dist-info/top_level.txt
django_deep_link-0.3.1.dist-info/RECORD
