Metadata-Version: 2.1
Name: django-deep-link
Version: 0.3.1
Summary: Simple app to get mobile app deep linking in place with basic tracking..
Author-email: Tim Santor <tsantor@xstudios.com>
Project-URL: Repository, https://github.com/tsantor/django-deep-link.git
Project-URL: Issues, https://github.com/tsantor/django-deep-link/issues
Project-URL: Changelog, https://github.com/tsantor/django-deep-link/blob/master/HISTORY.md
Classifier: Development Status :: 5 - Production/Stable
Classifier: Intended Audience :: Developers
Classifier: Natural Language :: English
Classifier: Programming Language :: Python :: 3.8
Classifier: Programming Language :: Python :: 3.9
Classifier: Programming Language :: Python :: 3.10
Classifier: Programming Language :: Python :: 3.11
Classifier: Programming Language :: Python :: 3.12
Requires-Python: >=3.8
License-File: LICENSE
License-File: AUTHORS.md
Requires-Dist: ua-parser
Requires-Dist: user-agents
Requires-Dist: django-ipware
Requires-Dist: requests
Provides-Extra: dev
